README.md
__init__.py
poetry.lock
pyproject.toml
setup.py
config/__init__.py
config/config.py
config/logging_config.py
data/beijing_house_price_test_data.csv
data/beijing_house_prices_2012_2017.csv
features/__init__.py
features/floors.py
features/moving_average.py
features/select_features.py
features/target_var.py
features/year_month_from_date.py
model/__init__.py
model/model_pipeline.py
model/predict.py
model/train.py
preprocessing/__init__.py
preprocessing/data_type_conversion.py
preprocessing/missing_data_imputer.py
preprocessing/select_rows.py
preprocessing/special_value_encoding.py
price_prediction_model.egg-info/PKG-INFO
price_prediction_model.egg-info/SOURCES.txt
price_prediction_model.egg-info/dependency_links.txt
price_prediction_model.egg-info/requires.txt
price_prediction_model.egg-info/top_level.txt
scripts/fetch_kaggle_dataset.sh
scripts/input_test.json
scripts/publish_model.sh
trained_model_files/lightgbm_regression_model_v1.0.2.pkl
utils/__init__.py
utils/errors.py
utils/generate_test_dataset.py
utils/utils.py
utils/validation.py