Metadata-Version: 2.1
Name: price-prediction-model
Version: 1.0.2
Summary: End to end lightGBM regression model to predict house prices in Beijing
Home-page: UNKNOWN
Author: Bowen
License: UNKNOWN
Platform: UNKNOWN
Requires-Python: ==3.*,>=3.7.0
Provides-Extra: dev
